cinnabar/__init__.py
cinnabar/_version.py
cinnabar/arsenic.py
cinnabar/plotlying.py
cinnabar/plotting.py
cinnabar/stats.py
cinnabar/wrangle.py
cinnabar/data/README.md
cinnabar/data/__init__.py
cinnabar/data/example.csv
cinnabar/tests/__init__.py
cinnabar/tests/conftest.py
cinnabar/tests/test_import.py
cinnabar/tests/test_stats.py
cinnabar/tests/test_wrangle.py
cinnabar-0.2.3.dist-info/LICENSE
cinnabar-0.2.3.dist-info/METADATA
cinnabar-0.2.3.dist-info/WHEEL
cinnabar-0.2.3.dist-info/entry_points.txt
cinnabar-0.2.3.dist-info/top_level.txt
cinnabar-0.2.3.dist-info/RECORD
