Metadata-Version: 2.1
Name: cinnabar
Version: 0.2.3
Author: Open Free Energy
Author-email: hannah.brucemacdonald@choderalab.org
License: MIT
License-File: LICENSE
